Tanisha_102103372/__init__.py
Tanisha_102103372-0.2.dist-info/LICENSE.txt
Tanisha_102103372-0.2.dist-info/METADATA
Tanisha_102103372-0.2.dist-info/WHEEL
Tanisha_102103372-0.2.dist-info/top_level.txt
Tanisha_102103372-0.2.dist-info/RECORD
