Metadata-Version: 2.1
Name: Tanisha-102103372
Version: 0.2
Summary: A python package for implementing topsis
Author: Tanisha Sood
Author-email: tsood1_be21@thapar.edu
Classifier: Programming Language :: Python :: 3
Classifier: License :: OSI Approved :: MIT License
Classifier: Operating System :: OS Independent
License-File: LICENSE.txt
